ewe/__init__.py
ewe/__main__.py
ewe-0.0.1.dist-info/METADATA
ewe-0.0.1.dist-info/WHEEL
ewe-0.0.1.dist-info/top_level.txt
ewe-0.0.1.dist-info/RECORD
