Metadata-Version: 2.1
Name: ewe
Version: 0.0.1
Summary: ewe build tool
Home-page: UNKNOWN
Author: rwxd
Author-email: rwxd@pm.me
License: MIT
Platform: UNKNOWN
